xiaopydesktop/__init__.py
xiaopydesktop/xiaopydesktop.cp38-win32.pyd
xiaopydesktop/xiaopydesktop.pyi
xiaopydesktop-1.0.8.dist-info/METADATA
xiaopydesktop-1.0.8.dist-info/WHEEL
xiaopydesktop-1.0.8.dist-info/top_level.txt
xiaopydesktop-1.0.8.dist-info/RECORD
